README.rst
setup.py
coffin_absolute/__init__.py
coffin_absolute.egg-info/PKG-INFO
coffin_absolute.egg-info/SOURCES.txt
coffin_absolute.egg-info/dependency_links.txt
coffin_absolute.egg-info/top_level.txt